airtrafficsim/__init__.py
airtrafficsim/_polars_array_api.py
airtrafficsim/column.py
airtrafficsim/plot.py
airtrafficsim/py.typed
airtrafficsim/quantity.py
airtrafficsim/types.py
airtrafficsim/unit_conversion.py
airtrafficsim/units.py
airtrafficsim/data/__init__.py
airtrafficsim/data/aircraft_types.py
airtrafficsim/data/airports.py
airtrafficsim/data/engine_emissions.py
airtrafficsim/data/era5.py
airtrafficsim/geospatial/__init__.py
airtrafficsim/geospatial/point.py
airtrafficsim/performance/__init__.py
airtrafficsim/performance/airspeed.py
airtrafficsim/performance/bada3.py
airtrafficsim/performance/isa.py
airtrafficsim/simulation/__init__.py
airtrafficsim/thermodynamics/__init__.py
airtrafficsim-0.2.0a4.dist-info/METADATA
airtrafficsim-0.2.0a4.dist-info/WHEEL
airtrafficsim-0.2.0a4.dist-info/licenses/LICENSE
airtrafficsim-0.2.0a4.dist-info/RECORD
