Metadata-Version: 2.4
Name: AirTrafficSim
Version: 0.2.0a4
Summary: A lightweight collection of tools for air traffic management research.
Project-URL: Repository, https://github.com/HKUST-OCTAD-LAB/AirTrafficSim
Author-email: Frankie Hui <kyhuiaf@connect.ust.hk>, Abraham Cheung <abraham@ylcheung.com>
License: MIT License
License-File: LICENSE
Keywords: air transportation,atm,simulations,visualisation
Classifier: Development Status :: 3 - Alpha
Classifier: Intended Audience :: Information Technology
Classifier: Intended Audience :: Science/Research
Classifier: License :: OSI Approved :: MIT License
Classifier: Operating System :: MacOS
Classifier: Operating System :: Microsoft :: Windows
Classifier: Operating System :: POSIX :: Linux
Classifier: Programming Language :: Python :: 3
Classifier: Programming Language :: Python :: 3.10
Classifier: Programming Language :: Python :: 3.11
Classifier: Programming Language :: Python :: 3.12
Classifier: Programming Language :: Python :: 3.13
Classifier: Topic :: Scientific/Engineering :: Physics
Classifier: Typing :: Typed
Requires-Python: >=3.10
Requires-Dist: annotated-types>=0.7.0
Requires-Dist: numpy>=2.2.0
Provides-Extra: all
Requires-Dist: httpx[http2]>=0.28.1; extra == 'all'
Requires-Dist: polars[calamine]>=1.18.0; extra == 'all'
Requires-Dist: xarray>=2024.11.0; extra == 'all'
Provides-Extra: era5
Requires-Dist: xarray>=2024.11.0; extra == 'era5'
Provides-Extra: jax
Requires-Dist: jax>=0.5.0; extra == 'jax'
Provides-Extra: networking
Requires-Dist: httpx[http2]>=0.28.1; extra == 'networking'
Provides-Extra: plot
Requires-Dist: matplotlib>=3.10.0; extra == 'plot'
Provides-Extra: polars
Requires-Dist: polars[calamine]>=1.18.0; extra == 'polars'
